swordartonline/__init__.py
swordartonline-2.2.10.dist-info/METADATA
swordartonline-2.2.10.dist-info/WHEEL
swordartonline-2.2.10.dist-info/top_level.txt
swordartonline-2.2.10.dist-info/RECORD
