Metadata-Version: 2.1
Name: swordartonline
Version: 2.2.10
Summary: Sample package
Author: Orange Alice
Author-email: author@example.com
Classifier: Programming Language :: Python :: 3
Classifier: License :: OSI Approved :: MIT License
Classifier: Operating System :: OS Independent
Requires-Python: >=3.6
